PyMaktube/MakTub.py
PyMaktube/MakTubSeqs.py
PyMaktube/Maktub.dll
PyMaktube/Maktub.so
PyMaktube/Probabilitys.py
PyMaktube/__init__.py
PyMaktube/ctypes.py
PyMakTub-0.1.2.dist-info/LICENSE
PyMakTub-0.1.2.dist-info/METADATA
PyMakTub-0.1.2.dist-info/WHEEL
PyMakTub-0.1.2.dist-info/top_level.txt
PyMakTub-0.1.2.dist-info/RECORD
