Metadata-Version: 2.1
Name: PyMakTub
Version: 0.1.2
Summary: A Procedural Generation Python Lib
Home-page: https://github.com/seuusuario/seurepositorio
Author: Mateus
Author-email: mateusmoutinho01@gmail.com
Classifier: Programming Language :: Python :: 3
Classifier: License :: OSI Approved :: MIT License
Classifier: Operating System :: OS Independent
Requires-Python: >=3.6
License-File: LICENSE
